rvlib/__init__.py
rvlib/_rmath_ffi.abi3.so
rvlib/metadata.yaml
rvlib/specials.py
rvlib/univariate.py
rvlib/version.py
rvlib-0.0.4.dist-info/LICENSE.txt
rvlib-0.0.4.dist-info/METADATA
rvlib-0.0.4.dist-info/WHEEL
rvlib-0.0.4.dist-info/top_level.txt
rvlib-0.0.4.dist-info/RECORD
