Metadata-Version: 2.1
Name: rvlib
Version: 0.0.4
Summary: Probability distributions mimicking Distrbutions.jl
Home-page: https://github.com/QuantEcon/rvlib
Author: Daniel Csaba, Spencer Lyon
Author-email: daniel.csaba@nyu.edu, spencer.lyon@stern.nyu.edu
License: UNKNOWN
Keywords: statistics,distributions
Platform: UNKNOWN
Requires-Dist: cffi (>=1.0.0)
Requires-Dist: numba (>=0.49)
Requires-Dist: numpy
Requires-Dist: PyYAML
